cairo_coverage/__init__.py
cairo_coverage/cairo_coverage.py
cairo_coverage-0.1.6.dist-info/METADATA
cairo_coverage-0.1.6.dist-info/WHEEL
cairo_coverage-0.1.6.dist-info/RECORD
