Metadata-Version: 2.1
Name: cairo-coverage
Version: 0.1.6
Summary: Cairo coverage module
Author: LucasLvy
Author-email: lucaslevy10@gmail.com
Requires-Python: >=3.9,<4.0
Classifier: Programming Language :: Python :: 3
Classifier: Programming Language :: Python :: 3.9
Classifier: Programming Language :: Python :: 3.10
Classifier: Programming Language :: Python :: 3.11
Requires-Dist: asynctest (>=0.13.0,<0.14.0)
Requires-Dist: cairo-lang (>=0.11,<0.12)
Requires-Dist: pytest (>=7.1.3,<8.0.0)
